oanda_chart/__init__.py
oanda_chart/chart_manager.py
oanda_chart/env/__init__.py
oanda_chart/env/const.py
oanda_chart/env/fonts.py
oanda_chart/env/initializer.py
oanda_chart/env/link_color.py
oanda_chart/geo/candle_offset.py
oanda_chart/geo/geo_candles.py
oanda_chart/geo/price_scale.py
oanda_chart/geo/scale_time.py
oanda_chart/geo/xandles.py
oanda_chart/geo/yrids.py
oanda_chart/image_data/AUD_anchor.png
oanda_chart/image_data/AUD_off.png
oanda_chart/image_data/AUD_on.png
oanda_chart/image_data/Base.PNG
oanda_chart/image_data/CAD_anchor.png
oanda_chart/image_data/CAD_off.png
oanda_chart/image_data/CAD_on.png
oanda_chart/image_data/CHF_anchor.png
oanda_chart/image_data/CHF_off.png
oanda_chart/image_data/CHF_on.png
oanda_chart/image_data/EUR_anchor.png
oanda_chart/image_data/EUR_off.png
oanda_chart/image_data/EUR_on.png
oanda_chart/image_data/GBP_anchor.png
oanda_chart/image_data/GBP_off.png
oanda_chart/image_data/GBP_on.png
oanda_chart/image_data/JPY_anchor.png
oanda_chart/image_data/JPY_off.png
oanda_chart/image_data/JPY_on.png
oanda_chart/image_data/NZD_anchor.png
oanda_chart/image_data/NZD_off.png
oanda_chart/image_data/NZD_on.png
oanda_chart/image_data/Quote.PNG
oanda_chart/image_data/USD_anchor.png
oanda_chart/image_data/USD_off.png
oanda_chart/image_data/USD_on.png
oanda_chart/selectors/__init__.py
oanda_chart/selectors/gran_menu.py
oanda_chart/selectors/pair_flags.py
oanda_chart/selectors/pair_menu.py
oanda_chart/selectors/quote_kind_menu.py
oanda_chart/selectors/selector.py
oanda_chart/util/__init__.py
oanda_chart/util/candle_range.py
oanda_chart/util/syntax_candy.py
oanda_chart/widgets/__init__.py
oanda_chart/widgets/chart_canvas.py
oanda_chart/widgets/oanda_chart.py
oanda_chart/widgets/price_canvas.py
oanda_chart/widgets/scale_canvas.py
oanda_chart/widgets/time_canvas.py
oanda_chart-0.1.3.dist-info/WHEEL
oanda_chart-0.1.3.dist-info/METADATA
oanda_chart-0.1.3.dist-info/RECORD
